{
    "title": "論文：第一次世界大戦の総合的研究 ― 起源、総力戦、そして現代世界への遺産",
    "outline": [
        {
            "level": "H1",
            "text": "論文：第一次世界大戦の総合的研究 ― 起源、総力戦、そして現代世界への遺産 ",
            "page": 0
        },
        {
            "level": "H2",
            "text": "序論 ",
            "page": 0
        },
        {
            "level": "H3",
            "text": "研究の目的と射程 ",
            "page": 0
        },
        {
            "level": "H3",
            "text": "問題意識 ",
            "page": 0
        },
        {
            "level": "H3",
            "text": "論文の構成 ",
            "page": 0
        },
        {
            "level": "H2",
            "text": "第一部：大戦への道―原因と勃発 ",
            "page": 1
        },
        {
            "level": "H3",
            "text": "第1章：長期的な対立の構造 ",
            "page": 1
        },
        {
            "level": "H4",
            "text": "1.1 帝国主義と植民地競争：アフリカ分割とモロッコ危機 ",
            "page": 1
        },
        {
            "level": "H4",
            "text": "1.2 軍国主義の台頭：英独建艦競争と陸軍の拡張 ",
            "page": 2
        },
        {
            "level": "H4",
            "text": "1.3 同盟システムの硬直化：三国同盟と三国協商 ",
            "page": 3
        },
        {
            "level": "H4",
            "text": "1.4 ナショナリズムの高揚：汎スラブ主義、フランスの復讐主義、そして「ヨーロッパの火薬庫」 ",
            "page": 3
        },
        {
            "level": "H3",
            "text": "第2章：1914年7月の危機と開戦 ",
            "page": 4
        },
        {
            "level": "H4",
            "text": "2.1 サラエボ事件：暗殺の衝撃 ",
            "page": 5
        },
        {
            "level": "H4",
            "text": "2.2 最後通牒と外交の失敗 ",
            "page": 5
        },
        {
            "level": "H4",
            "text": "2.3 シュリーフェン計画と戦争の連鎖反応 ",
            "page": 6
        },
        {
            "level": "H2",
            "text": "第二部：世界戦争の様相 ",
            "page": 10
        },
        {
            "level": "H3",
            "text": "第3章：主要戦線の展開 ",
            "page": 10
        },
        {
            "level": "H4",
            "text": "3.1 西部戦線：マルヌの奇跡から塹壕戦の泥沼へ ",
            "page": 10
        },
        {
            "level": "H4",
            "text": "3.2 東部戦線：タンネンベルクの戦いとブルシーロフ攻勢 ",
            "page": 11
        },
        {
            "level": "H4",
            "text": "3.3 その他の戦線：イタリア、バルカン、ガリポリ、中東 ",
            "page": 12
        },
        {
            "level": "H3",
            "text": "第4章：総力戦体制の構築 ",
            "page": 13
        },
        {
            "level": "H4",
            "text": "4.1 経済の動員：軍需生産と国家統制 ",
            "page": 13
        },
        {
            "level": "H4",
            "text": "4.2 銃後の国民：女性の社会進出、プロパガンダ、国民生活の変化 ",
            "page": 14
        },
        {
            "level": "H4",
            "text": "4.3 日本における総力戦認識の限界と大戦景気 ",
            "page": 14
        },
        {
            "level": "H3",
            "text": "第5章：戦争を変えた新技術 ",
            "page": 15
        },
        {
            "level": "H4",
            "text": "5.1 陸の戦い：機関銃、毒ガス、そして戦車の登場 ",
            "page": 15
        },
        {
            "level": "H4",
            "text": "5.2 海の戦い：ドレッドノート級戦艦と無制限潜水艦作戦 ",
            "page": 16
        },
        {
            "level": "H4",
            "text": "5.3 空の戦い：偵察機から戦闘機、戦略爆撃へ ",
            "page": 17
        },
        {
            "level": "H2",
            "text": "第三部：転換点と終結 ",
            "page": 17
        },
        {
            "level": "H3",
            "text": "第6章：グローバルな参戦国とその影響 ",
            "page": 18
        },
        {
            "level": "H4",
            "text": "6.1 ロシア革命とブレスト＝リトフスク条約 ",
            "page": 18
        },
        {
            "level": "H4",
            "text": "6.2 アメリカの参戦：経済的・軍事的帰結 ",
            "page": 18
        },
        {
            "level": "H4",
            "text": "6.3 日本の参戦とその戦略的意図：青島攻略、対華二十一カ条要求、地中海派遣 ",
            "page": 19
        },
        {
            "level": "H3",
            "text": "第7章：戦争の終結 ",
            "page": 20
        },
        {
            "level": "H4",
            "text": "7.1 1918年の最終攻勢：ドイツ春季攻勢と連合国の百日攻勢 ",
            "page": 20
        },
        {
            "level": "H4",
            "text": "7.2 中央同盟国の崩壊と休戦協定 ",
            "page": 21
        },
        {
            "level": "H2",
            "text": "第四部：大戦の遺産 ",
            "page": 22
        },
        {
            "level": "H3",
            "text": "第8章：ヴェルサイユ体制とその矛盾 ",
            "page": 22
        },
        {
            "level": "H4",
            "text": "8.1 パリ講和会議とヴェルサイユ条約の条項 ",
            "page": 22
        },
        {
            "level": "H4",
            "text": "8.2 帝国の解体と新国家の誕生 ",
            "page": 23
        },
        {
            "level": "H4",
            "text": "8.3 国際連盟の創設：成功と失敗 ",
            "page": 24
        },
        {
            "level": "H3",
            "text": "第9章：戦争の代償と記憶 ",
            "page": 25
        },
        {
            "level": "H4",
            "text": "9.1 人的・経済的損失の規模 ",
            "page": 25
        },
        {
            "level": "H4",
            "text": "9.2 社会・文化的変容と「失われた世代」 ",
            "page": 27
        },
        {
            "level": "H4",
            "text": "9.3 第一次世界大戦の歴史学：戦争責任をめぐる論争 ",
            "page": 27
        },
        {
            "level": "H2",
            "text": "結論：現代世界の起点としての大戦 ",
            "page": 28
        }
    ]
}